runner/__init__.py
runner/__main__.py
runner/runner.toml
runner_v1-0.1.1.dist-info/METADATA
runner_v1-0.1.1.dist-info/WHEEL
runner_v1-0.1.1.dist-info/entry_points.txt
runner_v1-0.1.1.dist-info/RECORD
